fakeid/__init__.py
fakeid-0.0.1.dist-info/LICENCE.txt
fakeid-0.0.1.dist-info/METADATA
fakeid-0.0.1.dist-info/WHEEL
fakeid-0.0.1.dist-info/top_level.txt
fakeid-0.0.1.dist-info/RECORD
